tensorwaves/__init__.py
tensorwaves/estimator.py
tensorwaves/interface.py
tensorwaves/py.typed
tensorwaves/version.py
tensorwaves/data/__init__.py
tensorwaves/data/_attrs.py
tensorwaves/data/_data_sample.py
tensorwaves/data/phasespace.py
tensorwaves/data/rng.py
tensorwaves/data/transform.py
tensorwaves/function/__init__.py
tensorwaves/function/_backend.py
tensorwaves/function/sympy/__init__.py
tensorwaves/function/sympy/_printer.py
tensorwaves/optimizer/__init__.py
tensorwaves/optimizer/callbacks.py
tensorwaves/optimizer/minuit.py
tensorwaves/optimizer/parameter.py
tensorwaves/optimizer/scipy.py
tensorwaves-0.4.14.dist-info/licenses/LICENSE
tensorwaves-0.4.14.dist-info/METADATA
tensorwaves-0.4.14.dist-info/WHEEL
tensorwaves-0.4.14.dist-info/top_level.txt
tensorwaves-0.4.14.dist-info/RECORD
