Metadata-Version: 2.4
Name: tensorwaves
Version: 0.4.14
Summary: Python fitter package for multiple computational back-ends
Author-email: Common Partial Wave Analysis <compwa-admin@ep1.rub.de>
Maintainer-email: compwa-admin@ep1.rub.de
License:                                  Apache License
Project-URL: Changelog, https://github.com/ComPWA/tensorwaves/releases
Project-URL: Documentation, https://tensorwaves.rtfd.io
Project-URL: Source, https://github.com/ComPWA/tensorwaves
Project-URL: Tracker, https://github.com/ComPWA/tensorwaves/issues
Keywords: HEP,PWA,amplitude analysis,partial wave analysis,particle physics,physics,tensorflow
Classifier: Development Status :: 4 - Beta
Classifier: Intended Audience :: Developers
Classifier: Intended Audience :: Education
Classifier: Intended Audience :: Science/Research
Classifier: License :: OSI Approved :: Apache Software License
Classifier: Natural Language :: English
Classifier: Operating System :: OS Independent
Classifier: Programming Language :: Python :: 3.10
Classifier: Programming Language :: Python :: 3.11
Classifier: Programming Language :: Python :: 3.12
Classifier: Programming Language :: Python :: 3.13
Classifier: Programming Language :: Python :: 3.9
Classifier: Programming Language :: Python
Classifier: Topic :: Scientific/Engineering :: Physics
Classifier: Topic :: Scientific/Engineering
Classifier: Typing :: Typed
Requires-Python: >=3.9
License-File: LICENSE
Requires-Dist: PyYAML>=5.1
Requires-Dist: attrs>=20.1.0
Requires-Dist: iminuit>=2.0
Requires-Dist: numpy
Requires-Dist: sympy>=1.9
Requires-Dist: tqdm>=4.24.0
Requires-Dist: typing-extensions; python_version < "3.10"
Provides-Extra: jax
Requires-Dist: jax; extra == "jax"
Requires-Dist: jaxlib; extra == "jax"
Provides-Extra: numba
Requires-Dist: numba; extra == "numba"
Provides-Extra: phsp
Requires-Dist: phasespace[tf]>=1.7.0; extra == "phsp"
Requires-Dist: tensorwaves[tf]; extra == "phsp"
Provides-Extra: pwa
Requires-Dist: ampform[viz]>=0.12.0; extra == "pwa"
Requires-Dist: tensorwaves[phsp]; extra == "pwa"
Provides-Extra: scipy
Requires-Dist: scipy>=1; extra == "scipy"
Provides-Extra: tf
Requires-Dist: tensorflow>=2.12; extra == "tf"
Dynamic: license-file
